{
    "<p>Senior Research fellow, Morgan Library; medieval manuscripts specialist.": [],
    "Plummer received his A.B.": [],
    "from Carleton College, Northfield, MN.": [
        [
            0,
            4,
            [
                "From"
            ]
        ]
    ],
    "He entered Columbia University in 1944, studying medieval art under <a href=\"/schapirer\">Meyer Schapiro</a>.": [],
    "As a graduate student, he taught art history courses.": [],
    "His lectures sparked the interest of <a href=\"/sandlerl\">Lucy Freeman Sandler</a> to be a manuscripts scholar.": [],
    "He received his Ph.D.": [],
    "in 1953 with a dissertation on a thirteenth-century English Illuminated Bible.": [
        [
            0,
            2,
            [
                "In"
            ]
        ]
    ],
    "Plummer was hired a Research associate at the Morgan Library in 1955, rising to curator for medieval and renaissance the following year.": [],
    "He taught at Barnard College 1952-1956.": [],
    "Among Plummer discoveries at the Morgan was the two halves of the Hours of Catherine of Cleves.": [],
    "In 1963 the Morgan bought an \"Hours of Catherine of Cleves\" (MS M.917), a Utrecht manuscript of about 1440.": [],
    "Plummer's study of the codex convinced him it was half of an elborately re-arranged single codex, the other portion belonging to a private collector, Alistair Bradley Martin.": [
        [
            61,
            71,
            [
                "elaborately"
            ]
        ]
    ],
    "In 1964 joined Columbia University as adjunct professor, publishing a facsimile of the book of hours in 1966.": [],
    "The same year he was named resesarch fellow for art at the Morgan.": [
        [
            27,
            36,
            [
                "research"
            ]
        ]
    ],
    "The Morgan purchased Martin's half of the Book of Hours (it became MS M.945) in 1970.": [],
    "He was named emeritus.</p>": []
}